digiseller_api_python/__init__.py
digiseller_api_python/_base_api.py
digiseller_api_python/_exceptions.py
digiseller_api_python/_request_handler.py
digiseller_api_python-3.1.2.dist-info/licenses/LICENSE
tests/__init__.py
tests/re_test.py
digiseller_api_python-3.1.2.dist-info/METADATA
digiseller_api_python-3.1.2.dist-info/WHEEL
digiseller_api_python-3.1.2.dist-info/top_level.txt
digiseller_api_python-3.1.2.dist-info/RECORD
