Metadata-Version: 2.4
Name: digiseller-api-python
Version: 3.1.2
Summary: Python wrapper package for easy integration with the Digiseller API
Home-page: https://github.com/Ernieleo/Digiseller-API-Python
Author: Ernieleo
Author-email: ernieleo@offnik.ru
Project-URL: API Documentation, https://my.digiseller.com/inside/api.asp
Project-URL: Write me, https://t.me/ernieleo
Keywords: digiseller api python wrapper
Classifier: Programming Language :: Python :: 3.8
Classifier: Programming Language :: Python :: 3.9
Classifier: Programming Language :: Python :: 3.10
Classifier: Programming Language :: Python :: 3.11
Classifier: Programming Language :: Python :: 3.12
Classifier: Programming Language :: Python :: 3.13
Classifier: Programming Language :: Python :: 3.14
Classifier: License :: OSI Approved :: MIT License
Classifier: Operating System :: OS Independent
Requires-Python: >=3.8
License-File: LICENSE
Requires-Dist: httpx>=0.26.0
Dynamic: author
Dynamic: author-email
Dynamic: classifier
Dynamic: description
Dynamic: description-content-type
Dynamic: home-page
Dynamic: keywords
Dynamic: license-file
Dynamic: project-url
Dynamic: requires-dist
Dynamic: requires-python
Dynamic: summary
